GridFree/__init__.py
GridFree/calculator.py
GridFree/crop.png
GridFree/dup1OUTPUT.tif
GridFree/seed.png
GridFree/seedsample.JPG
GridFree/tkinterGUI.py
GridFree/tkintercore.py
GridFree/tkintercorestat.py
GridFree/tkintersinglecore.py
GridFree/trainmodel.py
GridFree-0.1.2.2.dist-info/LICENSE
GridFree-0.1.2.2.dist-info/METADATA
GridFree-0.1.2.2.dist-info/WHEEL
GridFree-0.1.2.2.dist-info/top_level.txt
GridFree-0.1.2.2.dist-info/RECORD
