Metadata-Version: 2.1
Name: GridFree
Version: 0.1.2.2
Summary: label plants
Home-page: http://css.wsu.edu/people/research-associates/yang-hu/
Author: yangh
Author-email: yang.hu@wsu.edu
License: MIT Licence
Keywords: pip3,python3 -m pip,GridFree,droneimage,yanghu
Platform: any
Requires-Dist: pillow
Requires-Dist: opencv-python
Requires-Dist: matplotlib
Requires-Dist: scipy
Requires-Dist: sklearn
Requires-Dist: scikit-image
Requires-Dist: tkinter
Requires-Dist: rasterio
